py2opt/__init__.py
py2opt/constants.py
py2opt/routefinder.py
py2opt/solver.py
py2opt/utils.py
py2opt-1.4.1.dist-info/LICENSE.md
py2opt-1.4.1.dist-info/METADATA
py2opt-1.4.1.dist-info/WHEEL
py2opt-1.4.1.dist-info/entry_points.txt
py2opt-1.4.1.dist-info/top_level.txt
py2opt-1.4.1.dist-info/RECORD
