Metadata-Version: 2.1
Name: py2opt
Version: 1.4.1
Summary: How to solve the traveling salesman problem with the 2-opt algorithm
Home-page: https://github.com/pdrm83/py2opt
Author: Pedram Ataee
Author-email: pedram.ataee@gmail.com
License: MIT
Platform: UNKNOWN
Classifier: License :: OSI Approved :: MIT License
Classifier: Programming Language :: Python :: 3
Classifier: Programming Language :: Python :: 3.7
License-File: LICENSE.md
Requires-Dist: numpy
Requires-Dist: random2 (==1.0.1)
Requires-Dist: pytest
